{
	"map": {
		"rows": 20,
		"cols": 30,
		"terrain": [
			"xxxxxxx______________xxxxxxxxx",
			"xxxxxxx______________xxxxxxxxx",
			"xxxxxxx______________xxxxxxxxx",
			"__________________........_xxx",
			"__________________.______._xxx",
			"__________________.______._xxx",
			"__________________.______._xxx",
			"_____............_.______._xxx",
			"_____.__________._.______.__xx",
			"_____.__________...______.....",
			"_____.______________________xx",
			"_____._______________xx_____xx",
			"_____........____xxxxxx_____xx",
			"____________.____xxxxxx_____xx",
			"_______......____xxxxxx_____xx",
			"_______._________xxx________xx",
			"__......_________xxx________xx",
			"xx.xxxxxxxxxxxxxxxxxxxxxxxxxxx",
			"xx.xxxxxxxxxxxxxxxxxxxxxxxxxxx",
			"xx.xxxxxxxxxxxxxxxxxxxxxxxxxxx"
		],
		"starts": [
			[ 2, 19 ]
		],
		"finish": [ 29, 9 ],
		"paths": [
			[
				[ 2, 19 ],
				[ 2, 16 ],
				[ 7, 16 ],
				[ 7, 14 ],
				[ 12,14 ],
				[ 12,12 ],
				[ 5, 12 ],
				[ 5,  7 ],
				[ 16, 7 ],
				[ 16, 9 ],
				[ 18, 9 ],
				[ 18, 3 ],
				[ 25, 3 ],
				[ 25, 9 ],
				[ 29, 9 ]
			]
		]
	}
}
